vids_db_server/__init__.py
vids_db_server/app.py
vids_db_server/cmd.py
vids_db_server/date.py
vids_db_server/rss.py
vids_db_server/version.py
vids_db_server/www/index.html
vids_db_server/www/preview.jpg
vids_db_server-1.0.0.dist-info/LICENSE
vids_db_server-1.0.0.dist-info/METADATA
vids_db_server-1.0.0.dist-info/WHEEL
vids_db_server-1.0.0.dist-info/entry_points.txt
vids_db_server-1.0.0.dist-info/top_level.txt
vids_db_server-1.0.0.dist-info/RECORD
