Metadata-Version: 2.1
Name: vids-db-server
Version: 1.0.0
Summary: Server running vids_db
Home-page: https://github.com/zackees/vids-db-server
Author: Zach Vorhies
Author-email: dont@email.me
License: MIT
Platform: UNKNOWN
Classifier: License :: OSI Approved :: MIT License
Classifier: Programming Language :: Python :: 3.6
Classifier: Programming Language :: Python :: 3.9
Classifier: Operating System :: Microsoft :: Windows
Classifier: Operating System :: POSIX
Classifier: Operating System :: MacOS :: MacOS X
Classifier: Environment :: Console
Requires-Python: >=3.6.0
License-File: LICENSE
Requires-Dist: fastapi
Requires-Dist: requests
Requires-Dist: uvicorn[standard]
Requires-Dist: feedparser
Requires-Dist: vids-db (==1.1.4)
Provides-Extra: test
Requires-Dist: pytest ; extra == 'test'
